MANIFEST.in
README.md
setup.py
antispam/__init__.py
antispam/model.dat
antispam.egg-info/PKG-INFO
antispam.egg-info/SOURCES.txt
antispam.egg-info/dependency_links.txt
antispam.egg-info/top_level.txt