Metadata-Version: 1.1
Name: antispam
Version: 0.0.9
Summary: Bayesian anti-spam classifier written in Python.
Home-page: http://github.com/dinever/antispam
Author: Dinever
Author-email: dingpeixuan911@gmail.com
License: MIT License
Keywords: spam,filter,antispam
Platform: UNKNOWN
Classifier: Operating System :: Microsoft :: Windows
Classifier: Operating System :: MacOS :: MacOS X
Classifier: Operating System :: POSIX
Classifier: Natural Language :: English
Classifier: Programming Language :: Python :: 2.5
Classifier: Programming Language :: Python :: 2.6
Classifier: Programming Language :: Python :: 2.7
Classifier: Programming Language :: Python :: 3.4
Classifier: Programming Language :: Python :: 3.5
